localkhan/__init__.py
localkhan/serve.py
localkhan/loader.py
localkhan/cli.py
localkhan/tests/__init__.py
localkhan/tests/test_download.py
localkhan/templates/lkhan.appcache
localkhan/templates/index.html
localkhan/static/images/apple-touch-icon-72x72-precomposed.57b34622.png
localkhan/static/images/favicon.ico
localkhan/static/images/leaf-gold.7d34c320.svg
localkhan/static/images/leaf.b8974812.svg
localkhan/static/images/apple-touch-icon-114x114-precomposed.10c9cc08.png
localkhan/static/images/apple-touch-icon-144x144-precomposed.70e90002.png
localkhan/static/images/apple-touch-icon-57x57-precomposed.d97aee5a.png
localkhan/static/images/avatars/purple-pi.png
localkhan/static/images/avatars/marcimus.png
localkhan/static/images/avatars/orange-juice-squid.png
localkhan/static/images/avatars/spunky-sam.png
localkhan/static/images/avatars/mr-pink.png
localkhan/static/sound/question-correct.ogg
localkhan/static/sound/end-of-task.ogg
localkhan/static/styles/vendor.dd2bad85.css
localkhan/static/styles/main.1391714b.css
localkhan/static/styles/fonts/KaTeX_Math-BoldItalic.2d045c15.woff2
localkhan/static/styles/fonts/KaTeX_Main-Bold.9bd18abf.ttf
localkhan/static/styles/fonts/KaTeX_Size2-Regular.1c08cf63.woff2
localkhan/static/styles/fonts/KaTeX_Math-Regular.8a9b9d70.ttf
localkhan/static/styles/fonts/icomoon.d6c233a8.eot
localkhan/static/styles/fonts/KaTeX_Size2-Regular.bba967d7.eot
localkhan/static/styles/fonts/FontAwesome.0b462f5c.otf
localkhan/static/styles/fonts/KaTeX_Main-Italic.222d94ed.woff
localkhan/static/styles/fonts/KaTeX_Size2-Regular.fd7778be.ttf
localkhan/static/styles/fonts/KaTeX_Size4-Regular.3da4d6d5.ttf
localkhan/static/styles/fonts/KaTeX_Math-BoldItalic.e3840d61.ttf
localkhan/static/styles/fonts/KaTeX_Math-Regular.3a36cdbc.woff
localkhan/static/styles/fonts/KaTeX_Main-Regular.91602ac7.woff2
localkhan/static/styles/fonts/KaTeX_Size1-Regular.e8a2535b.woff2
localkhan/static/styles/fonts/KaTeX_Main-Bold.2403cc31.eot
localkhan-0.7.0.dist-info/metadata.json
localkhan-0.7.0.dist-info/DESCRIPTION.rst
localkhan-0.7.0.dist-info/LICENSE.txt
localkhan-0.7.0.dist-info/RECORD
localkhan-0.7.0.dist-info/METADATA
localkhan-0.7.0.dist-info/entry_points.txt
localkhan-0.7.0.dist-info/WHEEL
localkhan-0.7.0.dist-info/top_level.txt
