Metadata-Version: 2.0
Name: localkhan
Version: 0.7.0
Summary: Download and distribute Khan content
Home-page: http://github.com/aeby/localkhan/
Author: Reto Aebersold
Author-email: aeby@substyle.ch
License: MIT
Platform: any
Classifier: Development Status :: 4 - Beta
Classifier: Environment :: Web Environment
Classifier: Intended Audience :: Education
Classifier: License :: OSI Approved :: MIT License
Classifier: Operating System :: OS Independent
Classifier: Programming Language :: Python
Classifier: Programming Language :: Python :: 3
Classifier: Topic :: Education
Requires-Dist: requests (==2.7.0)
Requires-Dist: docopt (==0.6.2)
Requires-Dist: schema (==0.3.1)
Requires-Dist: clint (==0.4.1)
Requires-Dist: Flask (==0.10.1)
Requires-Dist: netifaces (==0.10.4)
Requires-Dist: pytube (==0.2.0)
